aio_throttle_to_next_second.py
aio_throttle_to_next_second-0.0.1.dist-info/LICENSE
aio_throttle_to_next_second-0.0.1.dist-info/METADATA
aio_throttle_to_next_second-0.0.1.dist-info/WHEEL
aio_throttle_to_next_second-0.0.1.dist-info/top_level.txt
aio_throttle_to_next_second-0.0.1.dist-info/RECORD
