Metadata-Version: 2.1
Name: aio-throttle-to-next-second
Version: 0.0.1
Summary: Throttler for asyncio Python that throttles to the next whole second
Home-page: https://github.com/uktrade/aio-throttle-to-next-second
Author: Michal Charemza
Author-email: michal@charemza.name
Maintainer: Department for International Trade
Maintainer-email: webops@digital.trade.gov.uk
License: UNKNOWN
Platform: UNKNOWN
Classifier: Programming Language :: Python :: 3
Classifier: License :: OSI Approved :: MIT License
Classifier: Operating System :: OS Independent
Classifier: Framework :: AsyncIO
Requires-Python: ~=3.5
